LICENSE.rst
LICENSE_GPL.rst
MANIFEST.in
README.rst
setup.py
src/agx/__init__.py
src/agx.transform.xmi2uml.egg-info/PKG-INFO
src/agx.transform.xmi2uml.egg-info/SOURCES.txt
src/agx.transform.xmi2uml.egg-info/dependency_links.txt
src/agx.transform.xmi2uml.egg-info/entry_points.txt
src/agx.transform.xmi2uml.egg-info/namespace_packages.txt
src/agx.transform.xmi2uml.egg-info/not-zip-safe
src/agx.transform.xmi2uml.egg-info/requires.txt
src/agx.transform.xmi2uml.egg-info/top_level.txt
src/agx/transform/__init__.py
src/agx/transform/xmi2uml/__init__.py
src/agx/transform/xmi2uml/configure.py
src/agx/transform/xmi2uml/configure.zcml
src/agx/transform/xmi2uml/interfaces.py
src/agx/transform/xmi2uml/tests.py
src/agx/transform/xmi2uml/transform.py
src/agx/transform/xmi2uml/transform.rst
src/agx/transform/xmi2uml/flavours/__init__.py
src/agx/transform/xmi2uml/flavours/xmi2_1.py
src/agx/transform/xmi2uml/testing/__init__.py
src/agx/transform/xmi2uml/testing/data/examplegg.uml
src/agx/transform/xmi2uml/testing/data/examplegg.umlclass
src/agx/transform/xmi2uml/testing/data/pyegg.profile.uml
src/agx/transform/xmi2uml/testing/data/pyegg.umlprofile